huaweicloudstoreplugin/__init__.py
huaweicloudstoreplugin/store/__init__.py
huaweicloudstoreplugin/store/artifact/__init__.py
huaweicloudstoreplugin/store/artifact/huaweicloud_obs_artifact_repo.py
huaweicloudstoreplugin-0.2.0.dist-info/LICENSE
huaweicloudstoreplugin-0.2.0.dist-info/METADATA
huaweicloudstoreplugin-0.2.0.dist-info/WHEEL
huaweicloudstoreplugin-0.2.0.dist-info/entry_points.txt
huaweicloudstoreplugin-0.2.0.dist-info/top_level.txt
huaweicloudstoreplugin-0.2.0.dist-info/RECORD
