Metadata-Version: 2.1
Name: huaweicloudstoreplugin
Version: 0.2.0
Summary: Plugin that provides Huawei Cloud OBS Artifact Store functionality for MLflow
Home-page: https://gitee.com/HuaweiCloudDeveloper/huaweicloud-mlflow-plugins
Author: HuaweiCloud
Author-email: 
License: Apache License 2.0
License-File: LICENSE
Requires-Dist: mlflow
Requires-Dist: esdk-obs-python >=3.23.9.1
